topsis/__init__.py
topsis/__main__.py
topsis_rahul_102218015-1.0.0.dist-info/LICENSE
topsis_rahul_102218015-1.0.0.dist-info/METADATA
topsis_rahul_102218015-1.0.0.dist-info/WHEEL
topsis_rahul_102218015-1.0.0.dist-info/entry_points.txt
topsis_rahul_102218015-1.0.0.dist-info/top_level.txt
topsis_rahul_102218015-1.0.0.dist-info/RECORD
